paten/__init__.py
paten/binding.py
paten/constants.py
paten/core.py
paten/error.py
paten/utils.py
paten/cli/__init__.py
paten/cli/factory.py
test/__init__.py
test/conftest.py
test/test_binding.py
test/test_cli.py
test/test_core.py
test/test_utils.py
paten-0.1.3.dist-info/METADATA
paten-0.1.3.dist-info/WHEEL
paten-0.1.3.dist-info/entry_points.txt
paten-0.1.3.dist-info/top_level.txt
paten-0.1.3.dist-info/RECORD
