Metadata-Version: 2.1
Name: paten
Version: 0.1.3
Summary: paten
Home-page: https://github.com/gsy0911/paten
Author: gsy0911
Author-email: yoshiki0911@gmail.com
License: MIT
Keywords: azure,azure functions
Platform: UNKNOWN
Classifier: Programming Language :: Python :: 3
Classifier: Programming Language :: Python :: 3.7
Classifier: Programming Language :: Python :: 3.8
Classifier: Development Status :: 3 - Alpha
Classifier: Operating System :: OS Independent
Classifier: Intended Audience :: Developers
Classifier: License :: OSI Approved :: MIT License
Requires-Python: >=3.7
Requires-Dist: click
Requires-Dist: azure-functions
